{"errors":[],"warnings":[],"namedChunkGroups":{"app":{"chunks":[5,0,2],"assets":["webpack-runtime-01110944bc16b30e05a8.js","webpack-runtime-01110944bc16b30e05a8.js.map","commons-f4e78fe3564ffcb553fc.js","commons-f4e78fe3564ffcb553fc.js.map","app-37e3ae3ed3b2db8bd70a.js","app-37e3ae3ed3b2db8bd70a.js.map"],"children":{},"childAssets":{}},"component---src-pages-404-js":{"chunks":[1,0,3],"assets":["styles.9e02df4f61f98c5c293f.css","styles-a6b646aa3a3a2179d6d5.js","styles-a6b646aa3a3a2179d6d5.js.map","commons-f4e78fe3564ffcb553fc.js","commons-f4e78fe3564ffcb553fc.js.map","component---src-pages-404-js-9db5708b4972809c6adb.js","component---src-pages-404-js-9db5708b4972809c6adb.js.map"],"children":{},"childAssets":{}},"component---src-pages-index-js":{"chunks":[1,0,4],"assets":["styles.9e02df4f61f98c5c293f.css","styles-a6b646aa3a3a2179d6d5.js","styles-a6b646aa3a3a2179d6d5.js.map","commons-f4e78fe3564ffcb553fc.js","commons-f4e78fe3564ffcb553fc.js.map","component---src-pages-index-js-a419af9379a3491090ca.js","component---src-pages-index-js-a419af9379a3491090ca.js.map"],"children":{},"childAssets":{}}},"assetsByChunkName":{"app":["webpack-runtime-01110944bc16b30e05a8.js","commons-f4e78fe3564ffcb553fc.js","app-37e3ae3ed3b2db8bd70a.js"],"component---src-pages-404-js":["styles.9e02df4f61f98c5c293f.css","styles-a6b646aa3a3a2179d6d5.js","commons-f4e78fe3564ffcb553fc.js","component---src-pages-404-js-9db5708b4972809c6adb.js"],"component---src-pages-index-js":["styles.9e02df4f61f98c5c293f.css","styles-a6b646aa3a3a2179d6d5.js","commons-f4e78fe3564ffcb553fc.js","component---src-pages-index-js-a419af9379a3491090ca.js"]}}